rocks/__init__.py
rocks/__main__.py
rocks/client.py
rocks/constants.py
rocks/server.py
rocks-0.1.7.dist-info/METADATA
rocks-0.1.7.dist-info/WHEEL
rocks-0.1.7.dist-info/entry_points.txt
rocks-0.1.7.dist-info/top_level.txt
rocks-0.1.7.dist-info/RECORD
