Metadata-Version: 2.1
Name: rocks
Version: 0.1.7
Summary: Long running RocksDB server like Redis Server so that you can interface with it without worrying about locks and multiprocessing primitives.
Home-page: https://www.github.com/Lamden/rocks
Author: Stuart Farmer
Author-email: stuart@lamden.io
License: GPL3
Platform: UNKNOWN
Requires-Dist: zcomm
Requires-Dist: pyzmq
Requires-Dist: python-rocksdb
